thoth/package_extract/__init__.py
thoth/package_extract/cli.py
thoth/package_extract/core.py
thoth/package_extract/exceptions.py
thoth/package_extract/image.py
thoth/package_extract/handlers/__init__.py
thoth/package_extract/handlers/base.py
thoth/package_extract/handlers/dnf.py
thoth/package_extract/handlers/pip.py
thoth/package_extract/handlers/pip3.py
thoth/package_extract/handlers/yum.py
thoth_package_extract-1.0.0.dist-info/DESCRIPTION.rst
thoth_package_extract-1.0.0.dist-info/METADATA
thoth_package_extract-1.0.0.dist-info/RECORD
thoth_package_extract-1.0.0.dist-info/WHEEL
thoth_package_extract-1.0.0.dist-info/entry_points.txt
thoth_package_extract-1.0.0.dist-info/metadata.json
thoth_package_extract-1.0.0.dist-info/top_level.txt
