Metadata-Version: 2.0
Name: thoth-package-extract
Version: 1.0.0
Summary: Tool and library for extracting packages from a docker build log
Home-page: https://github.com/fridex/thoth-package-extract
Author: Fridolin Pokorny
Author-email: fridolin@redhat.com
Maintainer: Fridolin Pokorny
Maintainer-email: fridolin@redhat.com
License: ASL v2.0
Keywords: docker image openshift tool library
Platform: UNKNOWN
Classifier: Development Status :: 4 - Beta
Classifier: Programming Language :: Python :: 3
Classifier: Programming Language :: Python :: 3.4
Classifier: Programming Language :: Python :: 3.5
Classifier: Environment :: Console
Classifier: Intended Audience :: Developers
Classifier: License :: OSI Approved :: Apache Software License
Classifier: Operating System :: OS Independent
Classifier: Programming Language :: Python :: Implementation :: CPython
Classifier: Programming Language :: Python :: Implementation :: PyPy
Requires-Dist: click
Requires-Dist: attrs
Requires-Dist: daiquiri
Requires-Dist: requests
Requires-Dist: thoth-common
Requires-Dist: thoth-analyzer (>=0.0.3)
